hippunfold_plot/__init__.py
hippunfold_plot/plotting.py
hippunfold_plot/utils.py
hippunfold_plot/resources/tpl-avg_hemi-left_space-canonical_label-hippdentate_density-0p5mm_midthickness.surf.gii
hippunfold_plot/resources/tpl-avg_hemi-left_space-canonical_label-hippdentate_density-1mm_midthickness.surf.gii
hippunfold_plot/resources/tpl-avg_hemi-left_space-canonical_label-hippdentate_density-2mm_midthickness.surf.gii
hippunfold_plot/resources/tpl-avg_hemi-left_space-canonical_label-hippdentate_density-unfoldiso_midthickness.surf.gii
hippunfold_plot/resources/tpl-avg_hemi-left_space-unfold_label-hippdentate_density-0p5mm_midthickness.surf.gii
hippunfold_plot/resources/tpl-avg_hemi-left_space-unfold_label-hippdentate_density-1mm_midthickness.surf.gii
hippunfold_plot/resources/tpl-avg_hemi-left_space-unfold_label-hippdentate_density-2mm_midthickness.surf.gii
hippunfold_plot/resources/tpl-avg_hemi-left_space-unfold_label-hippdentate_density-unfoldiso_midthickness.surf.gii
hippunfold_plot/resources/tpl-avg_hemi-right_space-canonical_label-hippdentate_density-0p5mm_midthickness.surf.gii
hippunfold_plot/resources/tpl-avg_hemi-right_space-canonical_label-hippdentate_density-1mm_midthickness.surf.gii
hippunfold_plot/resources/tpl-avg_hemi-right_space-canonical_label-hippdentate_density-2mm_midthickness.surf.gii
hippunfold_plot/resources/tpl-avg_hemi-right_space-canonical_label-hippdentate_density-unfoldiso_midthickness.surf.gii
hippunfold_plot/resources/tpl-avg_hemi-right_space-unfold_label-hippdentate_density-0p5mm_midthickness.surf.gii
hippunfold_plot/resources/tpl-avg_hemi-right_space-unfold_label-hippdentate_density-1mm_midthickness.surf.gii
hippunfold_plot/resources/tpl-avg_hemi-right_space-unfold_label-hippdentate_density-2mm_midthickness.surf.gii
hippunfold_plot/resources/tpl-avg_hemi-right_space-unfold_label-hippdentate_density-unfoldiso_midthickness.surf.gii
hippunfold_plot/resources/tpl-avg_label-hippdentate_density-0p5mm_curvature.shape.gii
hippunfold_plot-0.1.2.dist-info/LICENSE
hippunfold_plot-0.1.2.dist-info/METADATA
hippunfold_plot-0.1.2.dist-info/WHEEL
hippunfold_plot-0.1.2.dist-info/top_level.txt
hippunfold_plot-0.1.2.dist-info/RECORD
