Metadata-Version: 2.1
Name: hippunfold_plot
Version: 0.1.2
Summary: Plotting functions for hippocampal surface maps from HippUnfold
Requires-Python: >=3.9
License-File: LICENSE
Requires-Dist: matplotlib>=3.9.2
Requires-Dist: nilearn>=0.10.4
